sclients/__init__.py
sclients/rumor.py
sclients/runner.py
sclients/types.py
sclients/bin/__init__.py
sclients/bin/lighthouse_start
sclients/bin/lighthouse_stop
sclients/bin/prysm_start
sclients/bin/prysm_stop
sclients/bin/teku_start
sclients/bin/teku_stop
sclients/bin/__pycache__/__init__.cpython-38.pyc
stethoscope_clients-0.1.7.dist-info/LICENSE
stethoscope_clients-0.1.7.dist-info/METADATA
stethoscope_clients-0.1.7.dist-info/WHEEL
stethoscope_clients-0.1.7.dist-info/top_level.txt
stethoscope_clients-0.1.7.dist-info/RECORD
